COPYING
MANIFEST.in
README.rst
README.txt
coroner.py
setup.py
coroner.egg-info/PKG-INFO
coroner.egg-info/SOURCES.txt
coroner.egg-info/dependency_links.txt
coroner.egg-info/top_level.txt