Metadata-Version: 1.0
Name: coroner
Version: 0.2.1
Summary:  Wraps python invocations in code to do post-mortem debugging and sundry usefulnesses.
Home-page: http://github.com/intuited/coroner
Author: Ted Tibbetts
Author-email: intuited@gmail.com
License: UNKNOWN
Keywords: xml,grainery,odt,openoffice
Platform: UNKNOWN
Classifier: Development Status :: 2 - Pre-Alpha
Classifier: Intended Audience :: Developers
Classifier: License :: OSI Approved :: BSD License
Classifier: Operating System :: OS Independent
Classifier: Programming Language :: Python
Classifier: Programming Language :: Python :: 2
Classifier: Topic :: Software Development :: Libraries :: Python Modules
Classifier: Topic :: Utilities
Classifier: Topic :: Software Development :: Debuggers
